parsagon_local_drivers/__init__.py
parsagon_local_drivers-0.0.3.dist-info/LICENSE
parsagon_local_drivers-0.0.3.dist-info/METADATA
parsagon_local_drivers-0.0.3.dist-info/WHEEL
parsagon_local_drivers-0.0.3.dist-info/top_level.txt
parsagon_local_drivers-0.0.3.dist-info/RECORD
