Metadata-Version: 2.1
Name: parsagon-local-drivers
Version: 0.0.3
Summary: Parsagon Local Drivers
Home-page: https://parsagon.io
Author: Sandy Suh
Author-email: sandy@parsagon.io
License: UNKNOWN
Platform: UNKNOWN
Classifier: Programming Language :: Python :: 3
Classifier: License :: OSI Approved :: MIT License
Classifier: Operating System :: OS Independent
Requires-Python: >=3.6
License-File: LICENSE
Requires-Dist: chromedriver-binary-auto
Requires-Dist: selenium
Requires-Dist: websockets
